[
  {
    "file_path": "generated_graphs/nodes_100/removal_65percent/graph_16.edgelist",
    "num_nodes": 100,
    "percent_removed": 65,
    "iteration": 16,
    "greedy_mis_size": 12,
    "greedy_maximum_independent_set": [
      38,
      60,
      54,
      5,
      57,
      39,
      45,
      96,
      69,
      86,
      47,
      41
    ]
  },
  {
    "file_path": "generated_graphs/nodes_100/removal_65percent/graph_14.edgelist",
    "num_nodes": 100,
    "percent_removed": 65,
    "iteration": 14,
    "greedy_mis_size": 11,
    "greedy_maximum_independent_set": [
      35,
      65,
      68,
      81,
      45,
      22,
      59,
      49,
      12,
      63,
      61
    ]
  },
  {
    "file_path": "generated_graphs/nodes_100/removal_65percent/graph_1.edgelist",
    "num_nodes": 100,
    "percent_removed": 65,
    "iteration": 1,
    "greedy_mis_size": 12,
    "greedy_maximum_independent_set": [
      55,
      69,
      57,
      32,
      36,
      92,
      94,
      6,
      8,
      10,
      23,
      47
    ]
  },
  {
    "file_path": "generated_graphs/nodes_100/removal_65percent/graph_27.edgelist",
    "num_nodes": 100,
    "percent_removed": 65,
    "iteration": 27,
    "greedy_mis_size": 11,
    "greedy_maximum_independent_set": [
      31,
      4,
      8,
      51,
      76,
      42,
      57,
      70,
      11,
      17,
      2
    ]
  },
  {
    "file_path": "generated_graphs/nodes_100/removal_65percent/graph_26.edgelist",
    "num_nodes": 100,
    "percent_removed": 65,
    "iteration": 26,
    "greedy_mis_size": 11,
    "greedy_maximum_independent_set": [
      19,
      98,
      31,
      1,
      24,
      9,
      10,
      77,
      27,
      69,
      43
    ]
  },
  {
    "file_path": "generated_graphs/nodes_100/removal_65percent/graph_17.edgelist",
    "num_nodes": 100,
    "percent_removed": 65,
    "iteration": 17,
    "greedy_mis_size": 11,
    "greedy_maximum_independent_set": [
      97,
      90,
      46,
      54,
      64,
      93,
      31,
      6,
      65,
      39,
      49
    ]
  },
  {
    "file_path": "generated_graphs/nodes_100/removal_65percent/graph_2.edgelist",
    "num_nodes": 100,
    "percent_removed": 65,
    "iteration": 2,
    "greedy_mis_size": 11,
    "greedy_maximum_independent_set": [
      5,
      50,
      10,
      23,
      46,
      80,
      13,
      36,
      67,
      47,
      79
    ]
  },
  {
    "file_path": "generated_graphs/nodes_100/removal_65percent/graph_28.edgelist",
    "num_nodes": 100,
    "percent_removed": 65,
    "iteration": 28,
    "greedy_mis_size": 11,
    "greedy_maximum_independent_set": [
      14,
      21,
      1,
      71,
      12,
      64,
      63,
      73,
      33,
      25,
      39
    ]
  },
  {
    "file_path": "generated_graphs/nodes_100/removal_65percent/graph_24.edgelist",
    "num_nodes": 100,
    "percent_removed": 65,
    "iteration": 24,
    "greedy_mis_size": 12,
    "greedy_maximum_independent_set": [
      33,
      87,
      19,
      61,
      49,
      90,
      57,
      20,
      40,
      36,
      65,
      30
    ]
  },
  {
    "file_path": "generated_graphs/nodes_100/removal_65percent/graph_13.edgelist",
    "num_nodes": 100,
    "percent_removed": 65,
    "iteration": 13,
    "greedy_mis_size": 11,
    "greedy_maximum_independent_set": [
      49,
      7,
      66,
      21,
      27,
      63,
      0,
      19,
      14,
      9,
      32
    ]
  },
  {
    "file_path": "generated_graphs/nodes_100/removal_65percent/graph_10.edgelist",
    "num_nodes": 100,
    "percent_removed": 65,
    "iteration": 10,
    "greedy_mis_size": 11,
    "greedy_maximum_independent_set": [
      7,
      87,
      41,
      66,
      88,
      96,
      14,
      95,
      36,
      94,
      47
    ]
  },
  {
    "file_path": "generated_graphs/nodes_100/removal_65percent/graph_3.edgelist",
    "num_nodes": 100,
    "percent_removed": 65,
    "iteration": 3,
    "greedy_mis_size": 10,
    "greedy_maximum_independent_set": [
      80,
      21,
      43,
      56,
      23,
      73,
      82,
      47,
      2,
      41
    ]
  },
  {
    "file_path": "generated_graphs/nodes_100/removal_65percent/graph_30.edgelist",
    "num_nodes": 100,
    "percent_removed": 65,
    "iteration": 30,
    "greedy_mis_size": 11,
    "greedy_maximum_independent_set": [
      65,
      34,
      53,
      38,
      83,
      93,
      67,
      31,
      22,
      68,
      72
    ]
  },
  {
    "file_path": "generated_graphs/nodes_100/removal_65percent/graph_45.edgelist",
    "num_nodes": 100,
    "percent_removed": 65,
    "iteration": 45,
    "greedy_mis_size": 12,
    "greedy_maximum_independent_set": [
      13,
      58,
      26,
      64,
      93,
      86,
      66,
      77,
      57,
      70,
      52,
      41
    ]
  },
  {
    "file_path": "generated_graphs/nodes_100/removal_65percent/graph_33.edgelist",
    "num_nodes": 100,
    "percent_removed": 65,
    "iteration": 33,
    "greedy_mis_size": 10,
    "greedy_maximum_independent_set": [
      19,
      51,
      38,
      8,
      95,
      35,
      59,
      73,
      11,
      66
    ]
  },
  {
    "file_path": "generated_graphs/nodes_100/removal_65percent/graph_21.edgelist",
    "num_nodes": 100,
    "percent_removed": 65,
    "iteration": 21,
    "greedy_mis_size": 11,
    "greedy_maximum_independent_set": [
      83,
      7,
      31,
      35,
      76,
      53,
      27,
      97,
      25,
      33,
      16
    ]
  },
  {
    "file_path": "generated_graphs/nodes_100/removal_65percent/graph_39.edgelist",
    "num_nodes": 100,
    "percent_removed": 65,
    "iteration": 39,
    "greedy_mis_size": 11,
    "greedy_maximum_independent_set": [
      30,
      40,
      95,
      52,
      68,
      69,
      21,
      77,
      98,
      91,
      61
    ]
  },
  {
    "file_path": "generated_graphs/nodes_100/removal_65percent/graph_36.edgelist",
    "num_nodes": 100,
    "percent_removed": 65,
    "iteration": 36,
    "greedy_mis_size": 12,
    "greedy_maximum_independent_set": [
      57,
      46,
      20,
      58,
      6,
      91,
      34,
      37,
      43,
      49,
      27,
      3
    ]
  },
  {
    "file_path": "generated_graphs/nodes_100/removal_65percent/graph_32.edgelist",
    "num_nodes": 100,
    "percent_removed": 65,
    "iteration": 32,
    "greedy_mis_size": 10,
    "greedy_maximum_independent_set": [
      82,
      54,
      51,
      0,
      56,
      19,
      88,
      75,
      85,
      95
    ]
  },
  {
    "file_path": "generated_graphs/nodes_100/removal_65percent/graph_44.edgelist",
    "num_nodes": 100,
    "percent_removed": 65,
    "iteration": 44,
    "greedy_mis_size": 10,
    "greedy_maximum_independent_set": [
      0,
      95,
      59,
      98,
      81,
      52,
      92,
      23,
      78,
      73
    ]
  },
  {
    "file_path": "generated_graphs/nodes_100/removal_65percent/graph_46.edgelist",
    "num_nodes": 100,
    "percent_removed": 65,
    "iteration": 46,
    "greedy_mis_size": 12,
    "greedy_maximum_independent_set": [
      94,
      28,
      53,
      92,
      88,
      0,
      58,
      55,
      3,
      65,
      85,
      67
    ]
  },
  {
    "file_path": "generated_graphs/nodes_100/removal_65percent/graph_11.edgelist",
    "num_nodes": 100,
    "percent_removed": 65,
    "iteration": 11,
    "greedy_mis_size": 12,
    "greedy_maximum_independent_set": [
      5,
      59,
      71,
      73,
      50,
      53,
      77,
      17,
      68,
      26,
      51,
      34
    ]
  },
  {
    "file_path": "generated_graphs/nodes_100/removal_65percent/graph_38.edgelist",
    "num_nodes": 100,
    "percent_removed": 65,
    "iteration": 38,
    "greedy_mis_size": 11,
    "greedy_maximum_independent_set": [
      73,
      46,
      55,
      56,
      83,
      1,
      59,
      93,
      28,
      86,
      52
    ]
  },
  {
    "file_path": "generated_graphs/nodes_100/removal_65percent/graph_12.edgelist",
    "num_nodes": 100,
    "percent_removed": 65,
    "iteration": 12,
    "greedy_mis_size": 12,
    "greedy_maximum_independent_set": [
      88,
      55,
      29,
      89,
      5,
      25,
      6,
      41,
      79,
      10,
      58,
      36
    ]
  },
  {
    "file_path": "generated_graphs/nodes_100/removal_65percent/graph_40.edgelist",
    "num_nodes": 100,
    "percent_removed": 65,
    "iteration": 40,
    "greedy_mis_size": 11,
    "greedy_maximum_independent_set": [
      27,
      41,
      64,
      86,
      11,
      79,
      88,
      61,
      80,
      96,
      5
    ]
  },
  {
    "file_path": "generated_graphs/nodes_100/removal_65percent/graph_18.edgelist",
    "num_nodes": 100,
    "percent_removed": 65,
    "iteration": 18,
    "greedy_mis_size": 12,
    "greedy_maximum_independent_set": [
      78,
      59,
      2,
      90,
      38,
      68,
      24,
      45,
      79,
      93,
      65,
      50
    ]
  },
  {
    "file_path": "generated_graphs/nodes_100/removal_65percent/graph_23.edgelist",
    "num_nodes": 100,
    "percent_removed": 65,
    "iteration": 23,
    "greedy_mis_size": 12,
    "greedy_maximum_independent_set": [
      2,
      57,
      67,
      1,
      48,
      93,
      47,
      53,
      5,
      29,
      68,
      50
    ]
  },
  {
    "file_path": "generated_graphs/nodes_100/removal_65percent/graph_35.edgelist",
    "num_nodes": 100,
    "percent_removed": 65,
    "iteration": 35,
    "greedy_mis_size": 13,
    "greedy_maximum_independent_set": [
      61,
      71,
      53,
      30,
      73,
      25,
      87,
      15,
      18,
      70,
      34,
      31,
      77
    ]
  },
  {
    "file_path": "generated_graphs/nodes_100/removal_65percent/graph_37.edgelist",
    "num_nodes": 100,
    "percent_removed": 65,
    "iteration": 37,
    "greedy_mis_size": 12,
    "greedy_maximum_independent_set": [
      35,
      46,
      79,
      3,
      0,
      45,
      25,
      76,
      15,
      71,
      29,
      92
    ]
  },
  {
    "file_path": "generated_graphs/nodes_100/removal_65percent/graph_25.edgelist",
    "num_nodes": 100,
    "percent_removed": 65,
    "iteration": 25,
    "greedy_mis_size": 11,
    "greedy_maximum_independent_set": [
      87,
      20,
      63,
      11,
      94,
      6,
      44,
      72,
      67,
      46,
      56
    ]
  },
  {
    "file_path": "generated_graphs/nodes_100/removal_65percent/graph_22.edgelist",
    "num_nodes": 100,
    "percent_removed": 65,
    "iteration": 22,
    "greedy_mis_size": 12,
    "greedy_maximum_independent_set": [
      53,
      9,
      63,
      64,
      57,
      61,
      24,
      8,
      98,
      54,
      33,
      6
    ]
  },
  {
    "file_path": "generated_graphs/nodes_100/removal_65percent/graph_15.edgelist",
    "num_nodes": 100,
    "percent_removed": 65,
    "iteration": 15,
    "greedy_mis_size": 13,
    "greedy_maximum_independent_set": [
      66,
      20,
      4,
      41,
      74,
      15,
      89,
      67,
      57,
      81,
      6,
      99,
      50
    ]
  },
  {
    "file_path": "generated_graphs/nodes_100/removal_65percent/graph_8.edgelist",
    "num_nodes": 100,
    "percent_removed": 65,
    "iteration": 8,
    "greedy_mis_size": 12,
    "greedy_maximum_independent_set": [
      12,
      30,
      92,
      75,
      15,
      19,
      28,
      91,
      4,
      9,
      55,
      66
    ]
  },
  {
    "file_path": "generated_graphs/nodes_100/removal_65percent/graph_4.edgelist",
    "num_nodes": 100,
    "percent_removed": 65,
    "iteration": 4,
    "greedy_mis_size": 11,
    "greedy_maximum_independent_set": [
      24,
      92,
      8,
      35,
      46,
      72,
      57,
      76,
      78,
      60,
      1
    ]
  },
  {
    "file_path": "generated_graphs/nodes_100/removal_65percent/graph_50.edgelist",
    "num_nodes": 100,
    "percent_removed": 65,
    "iteration": 50,
    "greedy_mis_size": 11,
    "greedy_maximum_independent_set": [
      19,
      78,
      4,
      51,
      45,
      36,
      60,
      94,
      14,
      7,
      27
    ]
  },
  {
    "file_path": "generated_graphs/nodes_100/removal_65percent/graph_42.edgelist",
    "num_nodes": 100,
    "percent_removed": 65,
    "iteration": 42,
    "greedy_mis_size": 13,
    "greedy_maximum_independent_set": [
      46,
      40,
      53,
      69,
      88,
      92,
      6,
      41,
      44,
      82,
      95,
      42,
      65
    ]
  },
  {
    "file_path": "generated_graphs/nodes_100/removal_65percent/graph_48.edgelist",
    "num_nodes": 100,
    "percent_removed": 65,
    "iteration": 48,
    "greedy_mis_size": 12,
    "greedy_maximum_independent_set": [
      77,
      65,
      30,
      12,
      8,
      37,
      29,
      74,
      70,
      20,
      51,
      18
    ]
  },
  {
    "file_path": "generated_graphs/nodes_100/removal_65percent/graph_34.edgelist",
    "num_nodes": 100,
    "percent_removed": 65,
    "iteration": 34,
    "greedy_mis_size": 11,
    "greedy_maximum_independent_set": [
      4,
      72,
      65,
      55,
      85,
      12,
      93,
      88,
      27,
      79,
      51
    ]
  },
  {
    "file_path": "generated_graphs/nodes_100/removal_65percent/graph_20.edgelist",
    "num_nodes": 100,
    "percent_removed": 65,
    "iteration": 20,
    "greedy_mis_size": 12,
    "greedy_maximum_independent_set": [
      47,
      37,
      9,
      10,
      58,
      21,
      46,
      27,
      32,
      52,
      43,
      60
    ]
  },
  {
    "file_path": "generated_graphs/nodes_100/removal_65percent/graph_47.edgelist",
    "num_nodes": 100,
    "percent_removed": 65,
    "iteration": 47,
    "greedy_mis_size": 11,
    "greedy_maximum_independent_set": [
      71,
      30,
      53,
      62,
      37,
      17,
      79,
      54,
      40,
      87,
      41
    ]
  },
  {
    "file_path": "generated_graphs/nodes_100/removal_65percent/graph_49.edgelist",
    "num_nodes": 100,
    "percent_removed": 65,
    "iteration": 49,
    "greedy_mis_size": 11,
    "greedy_maximum_independent_set": [
      69,
      28,
      71,
      33,
      38,
      67,
      24,
      37,
      84,
      6,
      20
    ]
  },
  {
    "file_path": "generated_graphs/nodes_100/removal_65percent/graph_9.edgelist",
    "num_nodes": 100,
    "percent_removed": 65,
    "iteration": 9,
    "greedy_mis_size": 11,
    "greedy_maximum_independent_set": [
      90,
      78,
      46,
      6,
      87,
      36,
      98,
      67,
      37,
      92,
      50
    ]
  },
  {
    "file_path": "generated_graphs/nodes_100/removal_65percent/graph_19.edgelist",
    "num_nodes": 100,
    "percent_removed": 65,
    "iteration": 19,
    "greedy_mis_size": 12,
    "greedy_maximum_independent_set": [
      90,
      37,
      27,
      64,
      89,
      56,
      49,
      95,
      45,
      79,
      11,
      36
    ]
  },
  {
    "file_path": "generated_graphs/nodes_100/removal_65percent/graph_6.edgelist",
    "num_nodes": 100,
    "percent_removed": 65,
    "iteration": 6,
    "greedy_mis_size": 12,
    "greedy_maximum_independent_set": [
      58,
      39,
      70,
      42,
      22,
      7,
      65,
      84,
      20,
      38,
      87,
      68
    ]
  },
  {
    "file_path": "generated_graphs/nodes_100/removal_65percent/graph_29.edgelist",
    "num_nodes": 100,
    "percent_removed": 65,
    "iteration": 29,
    "greedy_mis_size": 13,
    "greedy_maximum_independent_set": [
      1,
      40,
      51,
      93,
      24,
      78,
      18,
      31,
      26,
      8,
      25,
      96,
      64
    ]
  },
  {
    "file_path": "generated_graphs/nodes_100/removal_65percent/graph_41.edgelist",
    "num_nodes": 100,
    "percent_removed": 65,
    "iteration": 41,
    "greedy_mis_size": 11,
    "greedy_maximum_independent_set": [
      20,
      26,
      27,
      39,
      8,
      41,
      93,
      59,
      57,
      43,
      46
    ]
  },
  {
    "file_path": "generated_graphs/nodes_100/removal_65percent/graph_31.edgelist",
    "num_nodes": 100,
    "percent_removed": 65,
    "iteration": 31,
    "greedy_mis_size": 12,
    "greedy_maximum_independent_set": [
      66,
      70,
      30,
      76,
      3,
      91,
      34,
      74,
      95,
      8,
      33,
      75
    ]
  },
  {
    "file_path": "generated_graphs/nodes_100/removal_65percent/graph_7.edgelist",
    "num_nodes": 100,
    "percent_removed": 65,
    "iteration": 7,
    "greedy_mis_size": 12,
    "greedy_maximum_independent_set": [
      76,
      24,
      20,
      1,
      82,
      4,
      86,
      21,
      41,
      94,
      11,
      68
    ]
  },
  {
    "file_path": "generated_graphs/nodes_100/removal_65percent/graph_43.edgelist",
    "num_nodes": 100,
    "percent_removed": 65,
    "iteration": 43,
    "greedy_mis_size": 13,
    "greedy_maximum_independent_set": [
      44,
      46,
      56,
      19,
      6,
      67,
      73,
      12,
      29,
      86,
      97,
      42,
      70
    ]
  },
  {
    "file_path": "generated_graphs/nodes_100/removal_65percent/graph_5.edgelist",
    "num_nodes": 100,
    "percent_removed": 65,
    "iteration": 5,
    "greedy_mis_size": 13,
    "greedy_maximum_independent_set": [
      70,
      14,
      74,
      69,
      77,
      61,
      29,
      15,
      57,
      62,
      27,
      7,
      91
    ]
  }
]