{
  "file_path": "generated_graphs/nodes_90/removal_80percent/graph_97.edgelist",
  "num_nodes": 90,
  "percent_removed": 80,
  "iteration": 97,
  "MIS_SIZE": 19,
  "MIS_SETS": [
    [
      2,
      9,
      10,
      15,
      21,
      24,
      27,
      46,
      47,
      48,
      49,
      50,
      52,
      55,
      69,
      74,
      85,
      88,
      89
    ],
    [
      2,
      9,
      10,
      15,
      21,
      33,
      46,
      47,
      48,
      50,
      52,
      55,
      69,
      74,
      81,
      85,
      86,
      88,
      89
    ],
    [
      2,
      9,
      10,
      21,
      24,
      27,
      46,
      47,
      48,
      49,
      50,
      52,
      55,
      68,
      69,
      74,
      85,
      88,
      89
    ],
    [
      2,
      9,
      10,
      21,
      33,
      46,
      47,
      48,
      50,
      52,
      55,
      68,
      69,
      74,
      81,
      85,
      86,
      88,
      89
    ]
  ],
  "MIS_CELLS": [
    0,
    0,
    1,
    0,
    0,
    0,
    0,
    0,
    0,
    1,
    1,
    0,
    0,
    0,
    0,
    1,
    0,
    0,
    0,
    0,
    0,
    1,
    0,
    0,
    1,
    0,
    0,
    1,
    0,
    0,
    0,
    0,
    0,
    1,
    0,
    0,
    0,
    0,
    0,
    0,
    0,
    0,
    0,
    0,
    0,
    0,
    1,
    1,
    1,
    1,
    1,
    0,
    1,
    0,
    0,
    1,
    0,
    0,
    0,
    0,
    0,
    0,
    0,
    0,
    0,
    0,
    0,
    0,
    1,
    1,
    0,
    0,
    0,
    0,
    1,
    0,
    0,
    0,
    0,
    0,
    0,
    1,
    0,
    0,
    0,
    1,
    1,
    0,
    1,
    1
  ],
  "MIS_CELLS_PROB": [
    0.0,
    0.0,
    1.0,
    0.0,
    0.0,
    0.0,
    0.0,
    0.0,
    0.0,
    1.0,
    1.0,
    0.0,
    0.0,
    0.0,
    0.0,
    0.5,
    0.0,
    0.0,
    0.0,
    0.0,
    0.0,
    1.0,
    0.0,
    0.0,
    0.5,
    0.0,
    0.0,
    0.5,
    0.0,
    0.0,
    0.0,
    0.0,
    0.0,
    0.5,
    0.0,
    0.0,
    0.0,
    0.0,
    0.0,
    0.0,
    0.0,
    0.0,
    0.0,
    0.0,
    0.0,
    0.0,
    1.0,
    1.0,
    1.0,
    0.5,
    1.0,
    0.0,
    1.0,
    0.0,
    0.0,
    1.0,
    0.0,
    0.0,
    0.0,
    0.0,
    0.0,
    0.0,
    0.0,
    0.0,
    0.0,
    0.0,
    0.0,
    0.0,
    0.5,
    1.0,
    0.0,
    0.0,
    0.0,
    0.0,
    1.0,
    0.0,
    0.0,
    0.0,
    0.0,
    0.0,
    0.0,
    0.5,
    0.0,
    0.0,
    0.0,
    1.0,
    0.5,
    0.0,
    1.0,
    1.0
  ]
}